cveforge
