Metadata-Version: 2.4
Name: cveforge
Version: 0.1.0
Summary: Framework that aim to enhance the developer experience for CVEs, malware, scans and reports. Aimed to Red and Blue cybersecurity teams.
Requires-Python: >=3.12
License-File: LICENSE
Requires-Dist: beautifulsoup4>=4.14.2
Requires-Dist: daphne>=4.2.1
Requires-Dist: django>=5.2.8
Requires-Dist: packaging>=25.0
Requires-Dist: paramiko>=4.0.0
Requires-Dist: pathspec>=0.12.1
Requires-Dist: pillow>=12.0.0
Requires-Dist: prompt-toolkit>=3.0.52
Requires-Dist: psutil>=7.1.3
Requires-Dist: requests>=2.32.5
Requires-Dist: rich>=14.2.0
Requires-Dist: scapy>=2.6.1
Requires-Dist: watchdog>=6.0.0
Requires-Dist: xmltodict>=1.0.2
Dynamic: license-file
